gptstonks/api/__init__.py
gptstonks/api/agent/__init__.py
gptstonks/api/agent/run_background.py
gptstonks/api/callbacks/__init__.py
gptstonks/api/callbacks/callbacks.py
gptstonks/api/constants/__init__.py
gptstonks/api/constants/constants.py
gptstonks/api/constants/env.py
gptstonks/api/data/openbb_v4.1.0_historical_vectorstoreindex_bgebaseen/default__vector_store.json
gptstonks/api/data/openbb_v4.1.0_historical_vectorstoreindex_bgebaseen/docstore.json
gptstonks/api/data/openbb_v4.1.0_historical_vectorstoreindex_bgebaseen/graph_store.json
gptstonks/api/data/openbb_v4.1.0_historical_vectorstoreindex_bgebaseen/image__vector_store.json
gptstonks/api/data/openbb_v4.1.0_historical_vectorstoreindex_bgebaseen/index_store.json
gptstonks/api/databases/__init__.py
gptstonks/api/databases/mongodb.py
gptstonks/api/explicability/__init__.py
gptstonks/api/explicability/explicability.py
gptstonks/api/initialization/__init__.py
gptstonks/api/initialization/app.py
gptstonks/api/main.py
gptstonks/api/models/__init__.py
gptstonks/api/models/data.py
gptstonks/api/models/query.py
gptstonks/api/models/response.py
gptstonks/api/routers/__init__.py
gptstonks/api/routers/tokens.py
gptstonks/api/utils/__init__.py
gptstonks/api/utils/openbb_chat_qa.py
gptstonks_api-0.0.1.dist-info/METADATA
gptstonks_api-0.0.1.dist-info/WHEEL
gptstonks_api-0.0.1.dist-info/RECORD
