Metadata-Version: 2.1
Name: gptstonks-api
Version: 0.0.1
Summary: GPTStonks API allows interacting with financial data sources using natural language.
Author-Email: GPTStonks <gptstonks@gmail.com>
License: MIT
Requires-Python: <3.11,>=3.10
Requires-Dist: pre-commit>=3.6.0
Requires-Dist: fastapi>=0.104.1
Requires-Dist: openbb==4.1.2
Requires-Dist: gptstonks-wrappers>=0.0.1.post3
Requires-Dist: uvicorn>=0.23.2
Requires-Dist: sentence-transformers>=2.2.2
Requires-Dist: duckduckgo-search>=5.2.1
Requires-Dist: wikipedia>=1.4.0
Requires-Dist: gdown>=4.7.1
Requires-Dist: boto3>=1.33.6
Requires-Dist: langchain>=0.1.11
Requires-Dist: llama-index>=0.10.18
Requires-Dist: python-dotenv>=1.0.0
Requires-Dist: openbb-alpha-vantage>=1.1.0
Requires-Dist: openbb-biztoc>=1.1.0
Requires-Dist: openbb-cboe>=1.1.0
Requires-Dist: openbb-ecb>=1.1.0
Requires-Dist: openbb-finra>=1.1.0
Requires-Dist: openbb-government-us>=1.1.0
Requires-Dist: openbb-nasdaq>=1.1.1
Requires-Dist: openbb-seeking-alpha>=1.1.0
Requires-Dist: openbb-stockgrid>=1.1.0
Requires-Dist: openbb-wsj>=1.1.0
Requires-Dist: pymongo>=4.6.1
Requires-Dist: langchain-openai>=0.0.8
Requires-Dist: langchainhub>=0.1.15
Requires-Dist: llama-index-llms-langchain>=0.1.3
Requires-Dist: llama-index-embeddings-openai>=0.1.6
Requires-Dist: llama-index-llms-huggingface>=0.1.3
Requires-Dist: llama-index-llms-openai>=0.1.7
Requires-Dist: llama-index-retrievers-bm25>=0.1.3
Requires-Dist: llama-index-embeddings-huggingface>=0.1.4
Requires-Dist: pytest; extra == "testing"
Requires-Dist: pytest-cov; extra == "testing"
Requires-Dist: trio>=0.23.2; extra == "testing"
Requires-Dist: pytest-asyncio>=0.23.2; extra == "testing"
Requires-Dist: trulens-eval>=0.25.1; extra == "testing"
Requires-Dist: llama-cpp-python>=0.2.23; extra == "llamacpp"
Requires-Dist: ipykernel>=6.29.3; extra == "notebooks"
Requires-Dist: ipython>=8.22.2; extra == "notebooks"
Requires-Dist: ipywidgets>=8.1.2; extra == "notebooks"
Provides-Extra: testing
Provides-Extra: llamacpp
Provides-Extra: notebooks
